obtuvi/__init__.py
obtuvi/ctypes.py
obtuvi/strategy/__init__.py
obtuvi/strategy/default.py
obtuvi/visitor/__init__.py
obtuvi/visitor/echo.py
obtuvi/visitor/jsonpatch.py
obtuvi-0.2.0.dist-info/LICENSE
obtuvi-0.2.0.dist-info/METADATA
obtuvi-0.2.0.dist-info/WHEEL
obtuvi-0.2.0.dist-info/top_level.txt
obtuvi-0.2.0.dist-info/RECORD
