Metadata-Version: 2.1
Name: obtuvi
Version: 0.2.0
Summary: ObTuVi
Author-email: Elmer Nocon <elmernocon@gmail.com>
License: MIT License
Requires-Python: >=3.9
License-File: LICENSE
Provides-Extra: dev
Requires-Dist: black ; extra == 'dev'
Requires-Dist: build ; extra == 'dev'
Requires-Dist: twine ; extra == 'dev'
Provides-Extra: test
Requires-Dist: PyYAML ; extra == 'test'
